symdiff/__init__.py
symdiff/symdiff_py3.so
symdiff-1.3.0.data/data/symdiff_data/LICENSE
symdiff-1.3.0.data/data/symdiff_data/NOTICE
symdiff-1.3.0.data/data/symdiff_data/README.md
symdiff-1.3.0.data/data/symdiff_data/doc/symdiff.pdf
symdiff-1.3.0.data/data/symdiff_data/examples/arrhenius.py
symdiff-1.3.0.data/data/symdiff_data/examples/arrhenius_py3.out
symdiff-1.3.0.data/data/symdiff_data/examples/deftest.py
symdiff-1.3.0.data/data/symdiff_data/examples/deftest_py3.out
symdiff-1.3.0.data/data/symdiff_data/examples/modellist1.py
symdiff-1.3.0.data/data/symdiff_data/examples/modellist1_py3.out
symdiff-1.3.0.data/data/symdiff_data/examples/models1.py
symdiff-1.3.0.data/data/symdiff_data/examples/models1_py3.out
symdiff-1.3.0.data/data/symdiff_data/examples/ordered.py
symdiff-1.3.0.data/data/symdiff_data/examples/ordered_py3.out
symdiff-1.3.0.data/data/symdiff_data/examples/parsetest.py
symdiff-1.3.0.data/data/symdiff_data/examples/parsetest_py3.out
symdiff-1.3.0.data/data/symdiff_data/examples/remove1.py
symdiff-1.3.0.data/data/symdiff_data/examples/remove1_py3.out
symdiff-1.3.0.data/data/symdiff_data/examples/subexpression1.py
symdiff-1.3.0.data/data/symdiff_data/examples/subexpression1_py3.out
symdiff-1.3.0.data/data/symdiff_data/examples/table.py
symdiff-1.3.0.data/data/symdiff_data/examples/table_py3.out
symdiff-1.3.0.data/data/symdiff_data/examples/undefined1.py
symdiff-1.3.0.data/data/symdiff_data/examples/undefined1_py3.out
symdiff-1.3.0.data/data/symdiff_data/examples/utf8.py
symdiff-1.3.0.data/data/symdiff_data/examples/utf8_py3.out
symdiff-1.3.0.dist-info/METADATA
symdiff-1.3.0.dist-info/WHEEL
symdiff-1.3.0.dist-info/top_level.txt
symdiff-1.3.0.dist-info/RECORD
symdiff-1.3.0.dist-info/licenses/LICENSE
symdiff-1.3.0.dist-info/licenses/NOTICE
