Metadata-Version: 2.4
Name: symdiff
Version: 1.3.0
Summary: SYMDIFF: Symbolic differentation of algebraic expressions
Home-page: https://symdiff.org
Author: DEVSIM LLC
Author-email: info@devsim.com
License: Apache License, Version 2.0
Project-URL: Bug Tracker, https://github.com/devsim/symdiff/issues
Project-URL: Source Code, https://github.com/devsim/symdiff
Project-URL: Online Forum, https://forum.devsim.org
Classifier: Development Status :: 5 - Production/Stable
Classifier: Intended Audience :: Science/Research
Classifier: License :: OSI Approved :: Apache Software License
Classifier: Programming Language :: Python :: 3
Classifier: Topic :: Scientific/Engineering :: Electronic Design Automation (EDA)
License-File: LICENSE
License-File: NOTICE
Dynamic: description
Dynamic: description-content-type
Dynamic: license-file
